my_package/__init__.py
my_package/data_processor.py
my_package/module1.py
my_package/module2.py
tests/__init__.py
tests/test_data_processor.py
tests/trst_module1.py
donald_first_package_2024-0.1.dist-info/METADATA
donald_first_package_2024-0.1.dist-info/WHEEL
donald_first_package_2024-0.1.dist-info/top_level.txt
donald_first_package_2024-0.1.dist-info/RECORD
