Metadata-Version: 2.1
Name: donald-first-package-2024
Version: 0.1
Summary: A package for processing data with pandas
Home-page: https://github.com/yourusername/my_package
Author: AchillesReaper
Author-email: your.email@example.com
License: UNKNOWN
Platform: UNKNOWN
Classifier: Programming Language :: Python :: 3
Classifier: License :: OSI Approved :: MIT License
Classifier: Operating System :: OS Independent
Requires-Python: >=3.6
Requires-Dist: pandas >=1.0
